{"latitude":20.625,"longitude":-105.25,"generationtime_ms":0.3660917282104492,"utc_offset_seconds":-21600,"timezone":"America/Mexico_City","timezone_abbreviation":"GMT-6","elevation":9.0,"current_units":{"time":"iso8601","interval":"seconds","temperature_2m":"°C","relative_humidity_2m":"%","apparent_temperature":"°C","weather_code":"wmo code","wind_speed_10m":"km/h"},"current":{"time":"2026-03-16T03:00","interval":900,"temperature_2m":24.8,"relative_humidity_2m":62,"apparent_temperature":26.3,"weather_code":0,"wind_speed_10m":6.9},"daily_units":{"time":"iso8601","weather_code":"wmo code","temperature_2m_max":"°C","temperature_2m_min":"°C"},"daily":{"time":["2026-03-16","2026-03-17","2026-03-18","2026-03-19","2026-03-20","2026-03-21","2026-03-22","2026-03-23"],"weather_code":[0,2,2,2,2,3,3,3],"temperature_2m_max":[26.8,26.1,25.9,25.9,25.9,25.9,25.8,30.7],"temperature_2m_min":[24.1,23.2,24.5,24.1,23.7,24.7,25.1,20.3]}}